yappa/__init__.py
yappa/cli.py
yappa/cli_helpers.py
yappa/config_generation.py
yappa/settings.py
yappa/utils.py
yappa/yappa.yaml
yappa/yappa_gw.yaml
yappa/handlers/__init__.py
yappa/handlers/asgi.py
yappa/handlers/common.py
yappa/handlers/manage.py
yappa/handlers/wsgi.py
yappa/packaging/__init__.py
yappa/packaging/common.py
yappa/packaging/direct.py
yappa/packaging/s3.py
yappa/yc/__init__.py
yappa/yc/access.py
yappa/yc/function_call.py
yappa/yc/functions.py
yappa/yc/gateway.py
yappa-0.4.30.dist-info/LICENSE
yappa-0.4.30.dist-info/METADATA
yappa-0.4.30.dist-info/WHEEL
yappa-0.4.30.dist-info/entry_points.txt
yappa-0.4.30.dist-info/top_level.txt
yappa-0.4.30.dist-info/RECORD
