Metadata-Version: 2.1
Name: yappa
Version: 0.4.30
Summary: Easy serverless deploy of python web applications
Home-page: https://github.com/turokg/yappa
Author: Egor Korovin
Author-email: kbkor@yandex.ru
License: MIT
Requires-Python: >=3.8.0
License-File: LICENSE
Requires-Dist: boto3>=1.10
Requires-Dist: click>=8.0
Requires-Dist: httpx==0.18
Requires-Dist: yandexcloud>=0.102.1
Requires-Dist: boltons>=21.0
Requires-Dist: idna<3,>=2.5
Requires-Dist: PyYAML>=5.0
Requires-Dist: furl>=2.0
Requires-Dist: pytz>=2021
